landowner/__init__.py
landowner/core.py
landowner/helpers.py
tests/deserializers/__init__.py
tests/deserializers/test_base.py
tests/deserializers/test_facebook.py
tests/deserializers/test_instagram.py
tests/entities/__init__.py
tests/entities/test_base.py
tests/entities/test_facebook.py
tests/entities/test_instagram.py
landowner-0.1.1.dist-info/LICENSE
landowner-0.1.1.dist-info/METADATA
landowner-0.1.1.dist-info/WHEEL
landowner-0.1.1.dist-info/top_level.txt
landowner-0.1.1.dist-info/RECORD
