Metadata-Version: 2.2
Name: landowner
Version: 0.1.1
Summary: A Python package for working with export files of your personal data from the big social media platforms.
Home-page: https://github.com/droptablerecords/landowner
Author: Drop Table Records
Author-email: info@droptablerecords.com
License:                     GNU GENERAL PUBLIC LICENSE
License-File: LICENSE
Dynamic: author
Dynamic: author-email
Dynamic: description
Dynamic: description-content-type
Dynamic: home-page
Dynamic: license
Dynamic: summary
